ionicons_python
