Metadata-Version: 2.1
Name: ionicons-python
Version: 1.0.3
Summary: Package containing icons taken from ionicons website.
Home-page: https://github.com/srang992/ionicons_python
Author: Subhradeep Rang
Author-email: srang992@gmail.com
License: MIT license
Keywords: ionicons_python
Classifier: Development Status :: 5 - Production/Stable
Classifier: Intended Audience :: Developers
Classifier: License :: OSI Approved :: MIT License
Classifier: Natural Language :: English
Classifier: Programming Language :: Python :: 3.7
Classifier: Programming Language :: Python :: 3.8
Classifier: Programming Language :: Python :: 3.9
Classifier: Programming Language :: Python :: 3.10
Requires-Python: >=3.7
License-File: LICENSE
License-File: AUTHORS.md
